naskit/__init__.py
naskit/algo/__init__.py
naskit/algo/levenshtein/__init__.py
naskit/algo/levenshtein/_levenshtein.cp39-win_amd64.pyd
naskit/algo/levenshtein/levenshtein.c
naskit/algo/ss_generation.py
naskit/containers/__init__.py
naskit/containers/graph.py
naskit/containers/nucleic_acid.py
naskit/containers/nucleic_acid_fragments.py
naskit/containers/nucleic_acid_graph.py
naskit/containers/pdb/__init__.py
naskit/containers/pdb/atom_name_mapping.py
naskit/containers/pdb/pdb_ss_parsing.py
naskit/containers/pdb/pdbAtom.py
naskit/containers/pdb/pdbContainer.py
naskit/containers/pdb/pdbDraw.py
naskit/containers/pdb/pdbMolecule.py
naskit/containers/pdb/pdbResidue.py
naskit/descriptors/__init__.py
naskit/descriptors/fragment_count.py
naskit/draw/__init__.py
naskit/draw/circular_graph.py
naskit/draw/config.py
naskit/draw/draw_na.py
naskit/draw/svg.py
naskit/exceptions.py
naskit/io/__init__.py
naskit/io/bna.py
naskit/io/bpseq.py
naskit/io/dot.py
naskit/io/dotLines.py
naskit/io/fasta.py
naskit/io/pdb.py
naskit/metrics/__init__.py
naskit/metrics/binary_classification.py
naskit/metrics/sequence.py
naskit/metrics/vector.py
naskit/parse_na.py
naskit/resources/pdb/adenine.pdb
naskit/resources/pdb/cytosine.pdb
naskit/resources/pdb/deoxyribose.pdb
naskit/resources/pdb/guanine.pdb
naskit/resources/pdb/ribose.pdb
naskit/resources/pdb/thymine.pdb
naskit/resources/pdb/uracil.pdb
naskit/utils/__init__.py
naskit/utils/math3d.py
naskit/utils/package_resources.py
naskit-0.10.0.dist-info/LICENSE
naskit-0.10.0.dist-info/METADATA
naskit-0.10.0.dist-info/WHEEL
naskit-0.10.0.dist-info/RECORD
